{
  "id": "47742447",
  "Pendientes": {
    "Aprobadas": [
      {
        "materia": "EFI",
        "curso": "4°4°",
        "fecha": "18/06/2024",
        "calificacion": "7",
        "id": 1,
        "libro": "16",
        "folio": "84"
      }
    ],
    "Adeuda": []
  },
  "preceptor": "MENDEZ AVILA GABRIEL A",
  "turno": "TM",
  "nombre": "CAMARGO WILLIAM ALEJANDRO",
  "dni": "47742447",
  "materias": [
    "LIT",
    "MCS",
    "EFI",
    "IGS",
    "PYC",
    "IAQ",
    "HTR",
    "GGF",
    "EMM",
    "DER",
    "GOR",
    "SIC"
  ],
  "curso": "5°2°",
  "informes": {
    "informe1": {
      "asistencia": {
        "Hábiles": "75",
        "Inasistencias": "10"
      },
      "materias": {
        "MCS": "TEP, , ",
        "DER": "TEP, , ",
        "GOR": "TED, , ",
        "LIT": "TEA, , ",
        "PYC": "TEA, , ",
        "GGF": "TEP, , ",
        "IGS": "TEP, , ",
        "EMM": "TEP, , ",
        "HTR": "TEA, , ",
        "SIC": "TEP, , ",
        "IAQ": "TEP, , ",
        "EFI": "TEP, , "
      }
    }
  }
}