{
  "id": "48219764",
  "dni": "48219764",
  "preceptor": "SILVELA DANIELA",
  "curso": "4°3°",
  "materias": [
    "LIT",
    "MCS",
    "EFI",
    "IGS",
    "NTI",
    "SYA",
    "IAF",
    "BLG",
    "HTR",
    "GGF",
    "SIC",
    "TDO"
  ],
  "turno": "TT",
  "informes": {
    "informe1": {
      "materias": {
        "IGS": "TEP, , ",
        "BLG": "TEP, , ",
        "SYA": "TEA, , ",
        "TDO": "TEA, , ",
        "EFI": "TEA, , ",
        "GGF": "TEP, , ",
        "HTR": "TEP, , ",
        "LIT": "TEP, , ",
        "MCS": "TEP, , ",
        "IAF": "TEP, , ",
        "NTI": "TEA, , ",
        "SIC": "TEA, , "
      },
      "asistencia": {
        "Inasistencias": "6",
        "Hábiles": "75"
      }
    }
  },
  "nombre": "BOYER DYLAN SAMUEL"
}