{
  "id": "49374144",
  "materias": [
    "BLG",
    "CCD",
    "EAR",
    "EFI",
    "FQA",
    "GGF",
    "HTR",
    "IGS",
    "MTM",
    "PLG"
  ],
  "Pendientes": {
    "Aprobadas": [],
    "Adeuda": [
      {
        "materia": "EFI",
        "curso": "2°1°",
        "id": 1
      }
    ]
  },
  "turno": "TM",
  "preceptor": "VILLAR CRISTIAN",
  "curso": "3°1°",
  "dni": "49374144",
  "informes": {
    "informe1": {
      "asistencia": {
        "Hábiles": "76",
        "Inasistencias": "5"
      },
      "materias": {
        "MTM": "TEP, , ",
        "IGS": "TEP, , ",
        "BLG": "TEA, , ",
        "CCD": "TEA, , ",
        "EFI": "TEA, , ",
        "FQA": "TEA, , ",
        "PLG": "TEA, , ",
        "HTR": "TEA, , ",
        "EAR": "TEA, , ",
        "GGF": "TEP, , "
      }
    },
    "informe2": {
      "asistencia": {
        "Inasistencias": "21",
        "Hábiles": "104"
      },
      "materias": {
        "EAR": "TEA, , ",
        "MTM": "TEA, , ",
        "EFI": "TEA, , ",
        "IGS": "TEP, , ",
        "HTR": "TEP, , ",
        "PLG": "TEA, , ",
        "FQA": "TEP, , ",
        "CCD": "TEP, , ",
        "GGF": "TEA, , ",
        "BLG": "TEA, , "
      }
    }
  },
  "nombre": "RICARDI UMA AGOSTINA"
}