{
  "id": "49525273",
  "nombre": "RODRIGUEZ LEONARDO MARTIN",
  "Pendientes": {
    "Adeuda": [
      {
        "materia": "IGS",
        "id": 1,
        "curso": "2°3°"
      },
      {
        "materia": "MTM",
        "id": 2,
        "curso": "2°3°"
      }
    ]
  },
  "dni": "49525273",
  "turno": "TT",
  "preceptor": "SILVELA DANIELA",
  "curso": "4°3°",
  "informes": {
    "informe1": {
      "asistencia": {
        "Inasistencias": "7",
        "Hábiles": "75"
      },
      "materias": {
        "IGS": "TEP, , ",
        "LIT": "TEP, , ",
        "GGF": "TEP, , ",
        "TDO": "TEA, , ",
        "IAF": "TEP, , ",
        "HTR": "TEP, , ",
        "MCS": "TEP, , ",
        "BLG": "TED, , ",
        "SIC": "TEA, , ",
        "EFI": "TEA, , ",
        "SYA": "TEA, , ",
        "NTI": "TEA, , "
      }
    }
  },
  "materias": [
    "LIT",
    "MCS",
    "EFI",
    "IGS",
    "NTI",
    "SYA",
    "IAF",
    "BLG",
    "HTR",
    "GGF",
    "SIC",
    "TDO"
  ]
}