{
  "id": "49624425",
  "informes": {
    "informe1": {
      "asistencia": {
        "Hábiles": "95",
        "Inasistencias": "11"
      },
      "materias": {
        "HTR": "TEA, , ",
        "CCD": "TEA, , ",
        "BLG": "TEA, , ",
        "GGF": "TEA, , ",
        "IGS": "TEA, , ",
        "FQA": "TEA, , ",
        "EFI": "TEA, , ",
        "PLG": "TEA, , ",
        "MTM": "TEA, , ",
        "EAR": "TEA, , "
      }
    }
  },
  "curso": "3°4°",
  "dni": "49624425",
  "nombre": "MACHADO VALENTIN LAUTARO",
  "materias": [
    "BLG",
    "CCD",
    "EAR",
    "EFI",
    "FQA",
    "GGF",
    "HTR",
    "IGS",
    "MTM",
    "PLG"
  ],
  "turno": "TT",
  "preceptor": "RYBARCZYK VALERIA"
}