{
  "id": "52586311",
  "preceptor": "SILVELA DANIELA",
  "curso": "1°2°",
  "nombre": "SONEZ GUADALUPE EDTH",
  "turno": "TT",
  "informes": {
    "informe1": {
      "asistencia": {
        "Hábiles": "75",
        "Inasistencias": "24"
      },
      "materias": {
        "EFI": "TEA, , ",
        "CNT": "TEP, , ",
        "MTM": "TEA, , ",
        "CCD": "TEA, , ",
        "IGS": "TEA, , ",
        "CSC": "TEP, , ",
        "PLG": "TEP, , ",
        "EAR": "TEA, , "
      }
    }
  },
  "materias": [
    "CNT",
    "CSC",
    "EAR",
    "EFI",
    "IGS",
    "MTM",
    "PLG",
    "CCD"
  ],
  "dni": "52586311"
}